timecraft/__init__.py
timecraft/client.py
timecraft/server.py
timecraft-0.0.1.dist-info/METADATA
timecraft-0.0.1.dist-info/WHEEL
timecraft-0.0.1.dist-info/top_level.txt
timecraft-0.0.1.dist-info/RECORD
