Metadata-Version: 2.1
Name: timecraft
Version: 0.0.1
Summary: SDK for the Timecraft runtime
Author-email: Stealth Rocket <contact@stealthrocket.tech>
Classifier: Programming Language :: Python :: 3
Classifier: Operating System :: OS Independent
Classifier: Environment :: WebAssembly :: WASI
Requires-Python: >=3.10
Requires-Dist: requests (>=2.31.0)
